falkonry.py
setup.cfg
setup.py
falkonry_cli.egg-info/PKG-INFO
falkonry_cli.egg-info/SOURCES.txt
falkonry_cli.egg-info/dependency_links.txt
falkonry_cli.egg-info/entry_points.txt
falkonry_cli.egg-info/not-zip-safe
falkonry_cli.egg-info/requires.txt
falkonry_cli.egg-info/top_level.txt