Metadata-Version: 1.1
Name: falkonry-cli
Version: 1.1.0
Summary: Cli tool to access Condition Prediction APIs
Home-page: https://github.com/Falkonry/falkonry-cli
Author: Falkonry Inc
Author-email: info@falkonry.com
License: MIT
Download-URL: https://github.com/Falkonry/falkonry-cli/tarball/1.1.0
Keywords: falkonry falkonryclient falkonrycli
Platform: UNKNOWN
